philistine/__init__.py
philistine/_base.py
philistine/mne/__init__.py
philistine/mne/_base.py
philistine/mne/io.py
philistine/mne/utils.py
philistine-0.1.dist-info/METADATA
philistine-0.1.dist-info/RECORD
philistine-0.1.dist-info/WHEEL
philistine-0.1.dist-info/top_level.txt
philistine-0.1.dist-info/zip-safe
