Metadata-Version: 2.1
Name: philistine
Version: 0.1
Summary: Utility functions for EEG and statistical analysis in Python
Home-page: https://gitlab.com/palday/philistine
Maintainer: Phillip Alday
Maintainer-email: phillip.alday@mpi.nl
License: BSD (3-clause)
Download-URL: https://gitlab.com/palday/philistine
Platform: any
Classifier: Intended Audience :: Science/Research
Classifier: Intended Audience :: Developers
Classifier: License :: OSI Approved
Classifier: Programming Language :: Python
Classifier: Topic :: Software Development
Classifier: Topic :: Scientific/Engineering
Classifier: Operating System :: Microsoft :: Windows
Classifier: Operating System :: POSIX
Classifier: Operating System :: Unix
Classifier: Operating System :: MacOS
